eph/__init__.py
eph/cli.py
eph/config.py
eph/eph.cfg
eph/exceptions.py
eph/horizons.py
eph/interface.py
eph/models.py
eph/parsers.py
eph/shortcuts.py
eph/util.py
test/__init__.py
test/conftest.py
test/test_cli.py
test/test_horizons.py
test/test_interface.py
test/test_models.py
test/test_parsers.py
test/test_util.py
test/__pycache__/__init__.cpython-37.pyc
test/__pycache__/conftest.cpython-37-PYTEST.pyc
test/__pycache__/test_cli.cpython-37-PYTEST.pyc
test/__pycache__/test_horizons.cpython-37-PYTEST.pyc
test/__pycache__/test_interface.cpython-37-PYTEST.pyc
test/__pycache__/test_models.cpython-37-PYTEST.pyc
test/__pycache__/test_parsers.cpython-37-PYTEST.pyc
test/__pycache__/test_util.cpython-37-PYTEST.pyc
test/res/config.ini
test/res/elements.ini
test/res/elements.txt
test/res/jpleph.txt
test/res/observer.ini
test/res/observer.txt
test/res/rosetta.ini
test/res/urls.txt
test/res/vectors.ini
test/res/vectors.txt
eph-1.1.4.dist-info/LICENSE
eph-1.1.4.dist-info/METADATA
eph-1.1.4.dist-info/WHEEL
eph-1.1.4.dist-info/entry_points.txt
eph-1.1.4.dist-info/top_level.txt
eph-1.1.4.dist-info/RECORD
