Metadata-Version: 2.1
Name: eph
Version: 1.1.4
Summary: Retrieve, represent and manipulate JPL Horizons ephemerides.
Home-page: https://github.com/bluephlavio/eph
Author: Flavio Grandin
Author-email: flavio.grandin@gmail.com
License: MIT
Platform: UNKNOWN
Classifier: Development Status :: 5 - Production/Stable
Classifier: Intended Audience :: Developers
Classifier: Intended Audience :: Science/Research
Classifier: License :: OSI Approved :: MIT License
Classifier: Natural Language :: English
Classifier: Operating System :: OS Independent
Classifier: Topic :: Scientific/Engineering :: Astronomy
Classifier: Topic :: Scientific/Engineering :: Physics
Classifier: Programming Language :: Python :: 3
Requires-Python: >=3.5
Requires-Dist: six (<2.0,>=1.0)
Requires-Dist: requests (<3.0,>=2.0)
Requires-Dist: astropy (<4.0,>=2.0)
